_mojo/_entrypoints.py
mojo-0.26.1.0.dist-info/WHEEL
mojo-0.26.1.0.dist-info/METADATA
mojo-0.26.1.0.dist-info/entry_points.txt
mojo-0.26.1.0.data/platlib/modular/bin/debugserver
mojo-0.26.1.0.data/platlib/modular/bin/gpu-query
mojo-0.26.1.0.data/platlib/modular/bin/lldb-argdumper
mojo-0.26.1.0.data/platlib/modular/bin/lldb-dap
mojo-0.26.1.0.data/platlib/modular/bin/llvm-symbolizer
mojo-0.26.1.0.data/platlib/modular/bin/mojo-lldb
mojo-0.26.1.0.data/platlib/modular/bin/mojo-lsp-server
mojo-0.26.1.0.data/platlib/modular/lib/lldb-visualizers/lldbDataFormatters.py
mojo-0.26.1.0.data/platlib/modular/lib/lldb-visualizers/mlirDataFormatters.py
mojo-0.26.1.0.data/platlib/modular/lib/mojo-repl-entry-point
mojo-0.26.1.0.dist-info/RECORD
