Metadata-Version: 2.1
Name: mojo
Author: Modular Inc
Author-email: hello@modular.com
Home-page: https://modular.com
License: LicenseRef-MAX-Platform-Software-License
Summary: The Mojo programming language
Project-URL: Changelog, https://docs.modular.com/mojo/changelog
Project-URL: Discord, https://discord.com/invite/modular
Project-URL: Documentation, https://docs.modular.com/mojo/
Project-URL: Forum, https://forum.modular.com/c/mojo
Project-URL: Issues, https://github.com/modular/modular/issues
Project-URL: Source, https://github.com/modular/modular/tree/main/mojo
Requires-Dist: mojo-compiler==0.26.1.0
Requires-Dist: mblack==26.1.0
Requires-Dist: mojo-lldb-libs==0.26.1.0
Version: 0.26.1.0
